Metadata-Version: 1.1
Name: mmuda-distributions
Version: 1.1
Summary: Gaussian and binomial distributions
Home-page: https://github.com/muellermax/
Author: Maximilian Müller
Author-email: UNKNOWN
License: UNKNOWN
Download-URL: https://github.com/muellermax/mmuda_distributions/archive/1.1.tar.gz
Keywords: binomial,gaussian,distribution,udacity
Platform: UNKNOWN
